Workbook

Sheet Products
A1: Business case: pelmeni SKU base economics
A2: Each row is one SKU. The 2×3 numeric matrix is B4:D5.
A3: SKU | B3: Base price | C3: Unit cost | D3: Base monthly units | F3: Why this sheet exists
A4: Classic Pelmeni 800g | B4: 420 | C4: 180 | D4: 1200 | F4: The owner wants to test how two pelmeni SKUs would perform
A5: Mini Pelmeni 500g | B5: 310 | C5: 135 | D5: 1800 | F5: across different sales channels before launching campaigns.
F6: Rows = products, columns = base economics.

Sheet Channels
A1: Business case: sales-channel / campaign modifiers
A2: Each row is one sales scenario. The 3×4 numeric matrix is B4:E6.
A3: Channel scenario | B3: Discount % | C3: Demand uplift % | D3: Logistics cost / unit | E3: Partner fee % | G3: Interpretation
A4: Own delivery (Novi Sad) | B4: 0 | C4: 0.1 | D4: 35 | E4: 0 | G4: Discount % lowers price.
A5: Local supermarket chain | B5: 0.12 | C5: 0.3 | D5: 22 | E5: 0.08 | G5: Demand uplift % increases expected units.
A6: Weekend food festival booth | B6: 0.05 | C6: 0.55 | D6: 48 | E6: 0.03 | G6: Logistics cost / unit covers delivery or stall operations.
G7: Partner fee % models marketplace / retailer take-rate.

Sheet CrossJoin
A1: Cross-join report: every SKU × every channel scenario
A2: This sheet is formula-driven. It enumerates all 2 × 3 combinations and computes price, volume, and gross profit for each scenario.
A3: SKU | B3: Base price | C3: Unit cost | D3: Base monthly units | E3: Channel scenario | F3: Discount % | G3: Demand uplift % | H3: Logistics cost / unit | I3: Partner fee % | J3: Adjusted price | K3: Forecast units | L3: Expected gross profit | N3: Formula for gross profit
A4: =Products!$A$4 -> Classic Pelmeni 800g | B4: =Products!$B$4 -> 420 | C4: =Products!$C$4 -> 180 | D4: =Products!$D$4 -> 1200 | E4: =Channels!$A$4 -> Own delivery (Novi Sad) | F4: =Channels!$B$4 -> 0 | G4: =Channels!$C$4 -> 0.1 | H4: =Channels!$D$4 -> 35 | I4: =Channels!$E$4 -> 0 | J4: =B4*(1-F4) -> 420 | K4: =D4*(1+G4) -> 1320 | L4: =K4*(J4-C4-H4-J4*I4) -> 270600 | N4: Forecast units × (Adjusted price − unit cost − logistics cost − channel fee)
A5: =Products!$A$4 -> Classic Pelmeni 800g | B5: =Products!$B$4 -> 420 | C5: =Products!$C$4 -> 180 | D5: =Products!$D$4 -> 1200 | E5: =Channels!$A$5 -> Local supermarket chain | F5: =Channels!$B$5 -> 0.12 | G5: =Channels!$C$5 -> 0.3 | H5: =Channels!$D$5 -> 22 | I5: =Channels!$E$5 -> 0.08 | J5: =B5*(1-F5) -> 369.6 | K5: =D5*(1+G5) -> 1560 | L5: =K5*(J5-C5-H5-J5*I5) -> 215329.92 | N5: This is a quick planning model, not full P&L.
A6: =Products!$A$4 -> Classic Pelmeni 800g | B6: =Products!$B$4 -> 420 | C6: =Products!$C$4 -> 180 | D6: =Products!$D$4 -> 1200 | E6: =Channels!$A$6 -> Weekend food festival booth | F6: =Channels!$B$6 -> 0.05 | G6: =Channels!$C$6 -> 0.55 | H6: =Channels!$D$6 -> 48 | I6: =Channels!$E$6 -> 0.03 | J6: =B6*(1-F6) -> 399 | K6: =D6*(1+G6) -> 1860 | L6: =K6*(J6-C6-H6-J6*I6) -> 295795.8
A7: =Products!$A$5 -> Mini Pelmeni 500g | B7: =Products!$B$5 -> 310 | C7: =Products!$C$5 -> 135 | D7: =Products!$D$5 -> 1800 | E7: =Channels!$A$4 -> Own delivery (Novi Sad) | F7: =Channels!$B$4 -> 0 | G7: =Channels!$C$4 -> 0.1 | H7: =Channels!$D$4 -> 35 | I7: =Channels!$E$4 -> 0 | J7: =B7*(1-F7) -> 310 | K7: =D7*(1+G7) -> 1980 | L7: =K7*(J7-C7-H7-J7*I7) -> 277200 | N7: Why cross join is useful
A8: =Products!$A$5 -> Mini Pelmeni 500g | B8: =Products!$B$5 -> 310 | C8: =Products!$C$5 -> 135 | D8: =Products!$D$5 -> 1800 | E8: =Channels!$A$5 -> Local supermarket chain | F8: =Channels!$B$5 -> 0.12 | G8: =Channels!$C$5 -> 0.3 | H8: =Channels!$D$5 -> 22 | I8: =Channels!$E$5 -> 0.08 | J8: =B8*(1-F8) -> 272.8 | K8: =D8*(1+G8) -> 2340 | L8: =K8*(J8-C8-H8-J8*I8) -> 219903.84 | N8: The owner sees every SKU-channel combination in one grid.
A9: =Products!$A$5 -> Mini Pelmeni 500g | B9: =Products!$B$5 -> 310 | C9: =Products!$C$5 -> 135 | D9: =Products!$D$5 -> 1800 | E9: =Channels!$A$6 -> Weekend food festival booth | F9: =Channels!$B$6 -> 0.05 | G9: =Channels!$C$6 -> 0.55 | H9: =Channels!$D$6 -> 48 | I9: =Channels!$E$6 -> 0.03 | J9: =B9*(1-F9) -> 294.5 | K9: =D9*(1+G9) -> 2790 | L9: =K9*(J9-C9-H9-J9*I9) -> 286435.35 | N9: That makes it easy to compare launch scenarios.
A10: Total expected gross profit | L10: =SUM(L4:L9) -> 1565264.9
